gantry/__init__.py
gantry/api_client.py
gantry/const.py
gantry/exceptions.py
gantry/globals.py
gantry/serializers.py
gantry/utils.py
gantry/validators.py
gantry/version.py
gantry/alerts/__init__.py
gantry/alerts/client.py
gantry/alerts/globals.py
gantry/alerts/main.py
gantry/applications/__init__.py
gantry/applications/client.py
gantry/applications/core.py
gantry/applications/llm.py
gantry/applications/llm_utils.py
gantry/applications/main.py
gantry/applications/utils.py
gantry/automations/__init__.py
gantry/automations/automations.py
gantry/automations/globals.py
gantry/automations/main.py
gantry/automations/actions/__init__.py
gantry/automations/actions/actions.py
gantry/automations/curators/__init__.py
gantry/automations/curators/curators.py
gantry/automations/curators/globals.py
gantry/automations/curators/main.py
gantry/automations/curators/models.py
gantry/automations/curators/selectors.py
gantry/automations/curators/stock_curators.py
gantry/automations/triggers/__init__.py
gantry/automations/triggers/triggers.py
gantry/cli/__init__.py
gantry/cli/application.py
gantry/cli/bucket.py
gantry/cli/data_connector.py
gantry/cli/main.py
gantry/cli/projection.py
gantry/cli/secret.py
gantry/data_generator/__init__.py
gantry/data_generator/data_generator.py
gantry/dataset/__init__.py
gantry/dataset/client.py
gantry/dataset/constants.py
gantry/dataset/gantry_dataset.py
gantry/dataset/main.py
gantry/dataset/templates/load_script_template.py.jinja
gantry/logger/__init__.py
gantry/logger/client.py
gantry/logger/constants.py
gantry/logger/consumer.py
gantry/logger/event_builder.py
gantry/logger/main.py
gantry/logger/stores.py
gantry/logger/types.py
gantry/logger/utils.py
gantry/query/__init__.py
gantry/query/client.py
gantry/query/globals.py
gantry/query/main.py
gantry/query/time_window.py
gantry/query/core/__init__.py
gantry/query/core/constants.py
gantry/query/core/dataframe.py
gantry/query/core/distance.py
gantry/query/core/metric.py
gantry/query/core/queryframe.py
gantry-0.6.14.dist-info/LICENSE
gantry-0.6.14.dist-info/METADATA
gantry-0.6.14.dist-info/WHEEL
gantry-0.6.14.dist-info/entry_points.txt
gantry-0.6.14.dist-info/top_level.txt
gantry-0.6.14.dist-info/RECORD
