Metadata-Version: 2.1
Name: gantry
Version: 0.6.14
Summary: Gantry Python Library
Author: Gantry Systems, Inc.
Author-email: oss@gantry.io
License: Apache Software License v2
Classifier: Development Status :: 4 - Beta
Classifier: Programming Language :: Python :: 3.7
Classifier: Programming Language :: Python :: 3.8
Classifier: Programming Language :: Python :: 3.9
Classifier: Programming Language :: Python :: 3.10
Classifier: Programming Language :: Python :: 3.11
Classifier: License :: OSI Approved :: Apache Software License
Classifier: Operating System :: OS Independent
Requires-Python: >=3.7
License-File: LICENSE
Requires-Dist: datasets ~=2.7.0
Requires-Dist: Jinja2 ~=3.1.2
Requires-Dist: dateparser >=1.1.1,~=1.1
Requires-Dist: typeguard ~=2.13
Requires-Dist: boto3-extensions >=0.11.0
Requires-Dist: backoff ~=2.1.2
Requires-Dist: click >=7.1.2
Requires-Dist: click-aliases ~=1.0
Requires-Dist: requests >=2.22.0
Requires-Dist: pyyaml >=5.3.1
Requires-Dist: colorama >=0.4.0
Requires-Dist: tabulate ~=0.8
Requires-Dist: typing-extensions >=4.6
Requires-Dist: halo ~=0.0.31
Requires-Dist: isodate ~=0.6
Requires-Dist: pydantic >=1.10.8
Requires-Dist: python-dateutil >=2.8.1
Requires-Dist: pandas
Requires-Dist: numpy
